{
  "Graph": {
    "P": 64,
    "M": 16,
    "m": 1048576,
    "S": 16384,
    "root": 0,
    "node_names": [
      "M0",
      "M1",
      "M2",
      "M3",
      "M4",
      "M5",
      "M6",
      "M7",
      "M8",
      "M9",
      "M10",
      "M11",
      "M12",
      "M13",
      "M14",
      "M15"
    ],
    "capacity": [
      4,
      4,
      4,
      4,
      4,
      4,
      4,
      4,
      4,
      4,
      4,
      4,
      4,
      4,
      4,
      4
    ],
    "net": "IB",
    "comms": {
      "edges": [
        [
          0,
          32
        ],
        [
          0,
          48
        ],
        [
          0,
          8
        ],
        [
          0,
          12
        ],
        [
          0,
          2
        ],
        [
          0,
          3
        ],
        [
          32,
          0
        ],
        [
          32,
          16
        ],
        [
          32,
          40
        ],
        [
          32,
          44
        ],
        [
          32,
          34
        ],
        [
          32,
          35
        ],
        [
          16,
          32
        ],
        [
          16,
          48
        ],
        [
          16,
          24
        ],
        [
          16,
          28
        ],
        [
          16,
          18
        ],
        [
          16,
          19
        ],
        [
          48,
          0
        ],
        [
          48,
          16
        ],
        [
          48,
          56
        ],
        [
          48,
          60
        ],
        [
          48,
          50
        ],
        [
          48,
          51
        ],
        [
          8,
          0
        ],
        [
          8,
          40
        ],
        [
          8,
          56
        ],
        [
          8,
          4
        ],
        [
          8,
          10
        ],
        [
          8,
          11
        ],
        [
          40,
          32
        ],
        [
          40,
          8
        ],
        [
          40,
          24
        ],
        [
          40,
          36
        ],
        [
          40,
          42
        ],
        [
          40,
          43
        ],
        [
          24,
          16
        ],
        [
          24,
          40
        ],
        [
          24,
          56
        ],
        [
          24,
          20
        ],
        [
          24,
          26
        ],
        [
          24,
          27
        ],
        [
          56,
          48
        ],
        [
          56,
          8
        ],
        [
          56,
          24
        ],
        [
          56,
          52
        ],
        [
          56,
          58
        ],
        [
          56,
          59
        ],
        [
          4,
          8
        ],
        [
          4,
          36
        ],
        [
          4,
          52
        ],
        [
          4,
          12
        ],
        [
          4,
          6
        ],
        [
          4,
          7
        ],
        [
          36,
          40
        ],
        [
          36,
          4
        ],
        [
          36,
          20
        ],
        [
          36,
          44
        ],
        [
          36,
          38
        ],
        [
          36,
          39
        ],
        [
          20,
          24
        ],
        [
          20,
          36
        ],
        [
          20,
          52
        ],
        [
          20,
          28
        ],
        [
          20,
          22
        ],
        [
          20,
          23
        ],
        [
          52,
          56
        ],
        [
          52,
          4
        ],
        [
          52,
          20
        ],
        [
          52,
          60
        ],
        [
          52,
          54
        ],
        [
          52,
          55
        ],
        [
          12,
          0
        ],
        [
          12,
          4
        ],
        [
          12,
          44
        ],
        [
          12,
          60
        ],
        [
          12,
          14
        ],
        [
          12,
          15
        ],
        [
          44,
          32
        ],
        [
          44,
          36
        ],
        [
          44,
          12
        ],
        [
          44,
          28
        ],
        [
          44,
          46
        ],
        [
          44,
          47
        ],
        [
          28,
          16
        ],
        [
          28,
          20
        ],
        [
          28,
          44
        ],
        [
          28,
          60
        ],
        [
          28,
          30
        ],
        [
          28,
          31
        ],
        [
          60,
          48
        ],
        [
          60,
          52
        ],
        [
          60,
          12
        ],
        [
          60,
          28
        ],
        [
          60,
          62
        ],
        [
          60,
          63
        ],
        [
          2,
          0
        ],
        [
          2,
          34
        ],
        [
          2,
          50
        ],
        [
          2,
          10
        ],
        [
          2,
          14
        ],
        [
          2,
          1
        ],
        [
          34,
          32
        ],
        [
          34,
          2
        ],
        [
          34,
          18
        ],
        [
          34,
          42
        ],
        [
          34,
          46
        ],
        [
          34,
          33
        ],
        [
          18,
          16
        ],
        [
          18,
          34
        ],
        [
          18,
          50
        ],
        [
          18,
          26
        ],
        [
          18,
          30
        ],
        [
          18,
          17
        ],
        [
          50,
          48
        ],
        [
          50,
          2
        ],
        [
          50,
          18
        ],
        [
          50,
          58
        ],
        [
          50,
          62
        ],
        [
          50,
          49
        ],
        [
          10,
          8
        ],
        [
          10,
          2
        ],
        [
          10,
          42
        ],
        [
          10,
          58
        ],
        [
          10,
          6
        ],
        [
          10,
          9
        ],
        [
          42,
          40
        ],
        [
          42,
          34
        ],
        [
          42,
          10
        ],
        [
          42,
          26
        ],
        [
          42,
          38
        ],
        [
          42,
          41
        ],
        [
          26,
          24
        ],
        [
          26,
          18
        ],
        [
          26,
          42
        ],
        [
          26,
          58
        ],
        [
          26,
          22
        ],
        [
          26,
          25
        ],
        [
          58,
          56
        ],
        [
          58,
          50
        ],
        [
          58,
          10
        ],
        [
          58,
          26
        ],
        [
          58,
          54
        ],
        [
          58,
          57
        ],
        [
          6,
          4
        ],
        [
          6,
          10
        ],
        [
          6,
          38
        ],
        [
          6,
          54
        ],
        [
          6,
          14
        ],
        [
          6,
          5
        ],
        [
          38,
          36
        ],
        [
          38,
          42
        ],
        [
          38,
          6
        ],
        [
          38,
          22
        ],
        [
          38,
          46
        ],
        [
          38,
          37
        ],
        [
          22,
          20
        ],
        [
          22,
          26
        ],
        [
          22,
          38
        ],
        [
          22,
          54
        ],
        [
          22,
          30
        ],
        [
          22,
          21
        ],
        [
          54,
          52
        ],
        [
          54,
          58
        ],
        [
          54,
          6
        ],
        [
          54,
          22
        ],
        [
          54,
          62
        ],
        [
          54,
          53
        ],
        [
          14,
          12
        ],
        [
          14,
          2
        ],
        [
          14,
          6
        ],
        [
          14,
          46
        ],
        [
          14,
          62
        ],
        [
          14,
          13
        ],
        [
          46,
          44
        ],
        [
          46,
          34
        ],
        [
          46,
          38
        ],
        [
          46,
          14
        ],
        [
          46,
          30
        ],
        [
          46,
          45
        ],
        [
          30,
          28
        ],
        [
          30,
          18
        ],
        [
          30,
          22
        ],
        [
          30,
          46
        ],
        [
          30,
          62
        ],
        [
          30,
          29
        ],
        [
          62,
          60
        ],
        [
          62,
          50
        ],
        [
          62,
          54
        ],
        [
          62,
          14
        ],
        [
          62,
          30
        ],
        [
          62,
          61
        ],
        [
          1,
          2
        ],
        [
          1,
          33
        ],
        [
          1,
          49
        ],
        [
          1,
          9
        ],
        [
          1,
          13
        ],
        [
          1,
          3
        ],
        [
          33,
          34
        ],
        [
          33,
          1
        ],
        [
          33,
          17
        ],
        [
          33,
          41
        ],
        [
          33,
          45
        ],
        [
          33,
          35
        ],
        [
          17,
          18
        ],
        [
          17,
          33
        ],
        [
          17,
          49
        ],
        [
          17,
          25
        ],
        [
          17,
          29
        ],
        [
          17,
          19
        ],
        [
          49,
          50
        ],
        [
          49,
          1
        ],
        [
          49,
          17
        ],
        [
          49,
          57
        ],
        [
          49,
          61
        ],
        [
          49,
          51
        ],
        [
          9,
          10
        ],
        [
          9,
          1
        ],
        [
          9,
          41
        ],
        [
          9,
          57
        ],
        [
          9,
          5
        ],
        [
          9,
          11
        ],
        [
          41,
          42
        ],
        [
          41,
          33
        ],
        [
          41,
          9
        ],
        [
          41,
          25
        ],
        [
          41,
          37
        ],
        [
          41,
          43
        ],
        [
          25,
          26
        ],
        [
          25,
          17
        ],
        [
          25,
          41
        ],
        [
          25,
          57
        ],
        [
          25,
          21
        ],
        [
          25,
          27
        ],
        [
          57,
          58
        ],
        [
          57,
          49
        ],
        [
          57,
          9
        ],
        [
          57,
          25
        ],
        [
          57,
          53
        ],
        [
          57,
          59
        ],
        [
          5,
          6
        ],
        [
          5,
          9
        ],
        [
          5,
          37
        ],
        [
          5,
          53
        ],
        [
          5,
          13
        ],
        [
          5,
          7
        ],
        [
          37,
          38
        ],
        [
          37,
          41
        ],
        [
          37,
          5
        ],
        [
          37,
          21
        ],
        [
          37,
          45
        ],
        [
          37,
          39
        ],
        [
          21,
          22
        ],
        [
          21,
          25
        ],
        [
          21,
          37
        ],
        [
          21,
          53
        ],
        [
          21,
          29
        ],
        [
          21,
          23
        ],
        [
          53,
          54
        ],
        [
          53,
          57
        ],
        [
          53,
          5
        ],
        [
          53,
          21
        ],
        [
          53,
          61
        ],
        [
          53,
          55
        ],
        [
          13,
          14
        ],
        [
          13,
          1
        ],
        [
          13,
          5
        ],
        [
          13,
          45
        ],
        [
          13,
          61
        ],
        [
          13,
          15
        ],
        [
          45,
          46
        ],
        [
          45,
          33
        ],
        [
          45,
          37
        ],
        [
          45,
          13
        ],
        [
          45,
          29
        ],
        [
          45,
          47
        ],
        [
          29,
          30
        ],
        [
          29,
          17
        ],
        [
          29,
          21
        ],
        [
          29,
          45
        ],
        [
          29,
          61
        ],
        [
          29,
          31
        ],
        [
          61,
          62
        ],
        [
          61,
          49
        ],
        [
          61,
          53
        ],
        [
          61,
          13
        ],
        [
          61,
          29
        ],
        [
          61,
          63
        ],
        [
          3,
          0
        ],
        [
          3,
          1
        ],
        [
          3,
          35
        ],
        [
          3,
          51
        ],
        [
          3,
          11
        ],
        [
          3,
          15
        ],
        [
          35,
          32
        ],
        [
          35,
          33
        ],
        [
          35,
          3
        ],
        [
          35,
          19
        ],
        [
          35,
          43
        ],
        [
          35,
          47
        ],
        [
          19,
          16
        ],
        [
          19,
          17
        ],
        [
          19,
          35
        ],
        [
          19,
          51
        ],
        [
          19,
          27
        ],
        [
          19,
          31
        ],
        [
          51,
          48
        ],
        [
          51,
          49
        ],
        [
          51,
          3
        ],
        [
          51,
          19
        ],
        [
          51,
          59
        ],
        [
          51,
          63
        ],
        [
          11,
          8
        ],
        [
          11,
          9
        ],
        [
          11,
          3
        ],
        [
          11,
          43
        ],
        [
          11,
          59
        ],
        [
          11,
          7
        ],
        [
          43,
          40
        ],
        [
          43,
          41
        ],
        [
          43,
          35
        ],
        [
          43,
          11
        ],
        [
          43,
          27
        ],
        [
          43,
          39
        ],
        [
          27,
          24
        ],
        [
          27,
          25
        ],
        [
          27,
          19
        ],
        [
          27,
          43
        ],
        [
          27,
          59
        ],
        [
          27,
          23
        ],
        [
          59,
          56
        ],
        [
          59,
          57
        ],
        [
          59,
          51
        ],
        [
          59,
          11
        ],
        [
          59,
          27
        ],
        [
          59,
          55
        ],
        [
          7,
          4
        ],
        [
          7,
          5
        ],
        [
          7,
          11
        ],
        [
          7,
          39
        ],
        [
          7,
          55
        ],
        [
          7,
          15
        ],
        [
          39,
          36
        ],
        [
          39,
          37
        ],
        [
          39,
          43
        ],
        [
          39,
          7
        ],
        [
          39,
          23
        ],
        [
          39,
          47
        ],
        [
          23,
          20
        ],
        [
          23,
          21
        ],
        [
          23,
          27
        ],
        [
          23,
          39
        ],
        [
          23,
          55
        ],
        [
          23,
          31
        ],
        [
          55,
          52
        ],
        [
          55,
          53
        ],
        [
          55,
          59
        ],
        [
          55,
          7
        ],
        [
          55,
          23
        ],
        [
          55,
          63
        ],
        [
          15,
          12
        ],
        [
          15,
          13
        ],
        [
          15,
          3
        ],
        [
          15,
          7
        ],
        [
          15,
          47
        ],
        [
          15,
          63
        ],
        [
          47,
          44
        ],
        [
          47,
          45
        ],
        [
          47,
          35
        ],
        [
          47,
          39
        ],
        [
          47,
          15
        ],
        [
          47,
          31
        ],
        [
          31,
          28
        ],
        [
          31,
          29
        ],
        [
          31,
          19
        ],
        [
          31,
          23
        ],
        [
          31,
          47
        ],
        [
          31,
          63
        ],
        [
          63,
          60
        ],
        [
          63,
          61
        ],
        [
          63,
          51
        ],
        [
          63,
          55
        ],
        [
          63,
          15
        ],
        [
          63,
          31
        ]
      ],
      "volume": [
        115341,
        115341,
        117994,
        117994,
        120808,
        120808,
        115356,
        115371,
        117994,
        117994,
        120808,
        120808,
        115341,
        115341,
        117994,
        117994,
        120808,
        120808,
        115371,
        115356,
        117994,
        117994,
        120808,
        120808,
        118009,
        115341,
        115341,
        118024,
        120808,
        120808,
        118009,
        115356,
        115371,
        118024,
        120808,
        120808,
        118009,
        115341,
        115341,
        118024,
        120808,
        120808,
        118009,
        115371,
        115356,
        118024,
        120808,
        120808,
        117994,
        115341,
        115341,
        117994,
        120808,
        120808,
        117994,
        115356,
        115371,
        117994,
        120808,
        120808,
        117994,
        115341,
        115341,
        117994,
        120808,
        120808,
        117994,
        115371,
        115356,
        117994,
        120808,
        120808,
        118024,
        118009,
        115341,
        115341,
        120808,
        120808,
        118024,
        118009,
        115356,
        115371,
        120808,
        120808,
        118024,
        118009,
        115341,
        115341,
        120808,
        120808,
        118024,
        118009,
        115371,
        115356,
        120808,
        120808,
        120824,
        115341,
        115341,
        117994,
        117994,
        120839,
        120824,
        115356,
        115371,
        117994,
        117994,
        120839,
        120824,
        115341,
        115341,
        117994,
        117994,
        120839,
        120824,
        115371,
        115356,
        117994,
        117994,
        120839,
        120824,
        118009,
        115341,
        115341,
        118024,
        120839,
        120824,
        118009,
        115356,
        115371,
        6,
        118024,
        20,
        120839,
        60,
        120824,
        118009,
        115341,
        115341,
        118024,
        120839,
        120824,
        118009,
        115371,
        6,
        115356,
        118024,
        20,
        120839,
        60,
        120824,
        117994,
        115341,
        115341,
        117994,
        120839,
        120824,
        117994,
        115356,
        115371,
        117994,
        120839,
        120824,
        117994,
        115341,
        115341,
        117994,
        120839,
        120824,
        117994,
        115371,
        115356,
        117994,
        120839,
        120824,
        118024,
        118009,
        115341,
        115341,
        120839,
        120824,
        118024,
        20,
        118009,
        115356,
        115371,
        6,
        120839,
        60,
        120824,
        118024,
        118009,
        115341,
        115341,
        120839,
        120824,
        118024,
        20,
        118009,
        115371,
        6,
        115356,
        120839,
        60,
        120808,
        115341,
        115341,
        117994,
        117994,
        120808,
        120808,
        115356,
        115371,
        117994,
        117994,
        120808,
        120808,
        115341,
        115341,
        117994,
        117994,
        120808,
        120808,
        115371,
        115356,
        117994,
        117994,
        120808,
        120808,
        118009,
        115341,
        115341,
        118024,
        120808,
        120808,
        118009,
        115356,
        115371,
        118024,
        120808,
        120808,
        118009,
        115341,
        115341,
        118024,
        120808,
        120808,
        118009,
        115371,
        115356,
        118024,
        120808,
        120808,
        117994,
        115341,
        115341,
        117994,
        120808,
        120808,
        117994,
        115356,
        115371,
        117994,
        120808,
        120808,
        117994,
        115341,
        115341,
        117994,
        120808,
        120808,
        117994,
        115371,
        115356,
        117994,
        120808,
        120808,
        118024,
        118009,
        115341,
        115341,
        120808,
        120808,
        118024,
        118009,
        115356,
        115371,
        120808,
        120808,
        118024,
        118009,
        115341,
        115341,
        120808,
        120808,
        118024,
        118009,
        115371,
        115356,
        120808,
        120839,
        120824,
        115341,
        115341,
        117994,
        117994,
        120839,
        120824,
        115356,
        115371,
        117994,
        117994,
        120839,
        120824,
        115341,
        115341,
        117994,
        117994,
        120839,
        120824,
        115371,
        115356,
        117994,
        117994,
        120839,
        120824,
        118009,
        115341,
        115341,
        118024,
        120839,
        60,
        120824,
        118009,
        115356,
        115371,
        6,
        118024,
        20,
        120839,
        120824,
        118009,
        115341,
        115341,
        118024,
        120839,
        60,
        120824,
        118009,
        115371,
        6,
        115356,
        118024,
        20,
        120839,
        120824,
        117994,
        115341,
        115341,
        117994,
        120839,
        120824,
        117994,
        115356,
        115371,
        117994,
        120839,
        120824,
        117994,
        115341,
        115341,
        117994,
        120839,
        120824,
        117994,
        115371,
        115356,
        117994,
        120839,
        120824,
        118024,
        118009,
        115341,
        115341,
        120839,
        60,
        120824,
        118024,
        20,
        118009,
        115356,
        115371,
        6,
        120839,
        120824,
        118024,
        118009,
        115341,
        115341,
        120839,
        60,
        120824,
        118024,
        20,
        118009,
        115371,
        6,
        115356
      ],
      "n_msgs": [
        5,
        5,
        5,
        5,
        5,
        5,
        5,
        5,
        5,
        5,
        5,
        5,
        5,
        5,
        5,
        5,
        5,
        5,
        5,
        5,
        5,
        5,
        5,
        5,
        5,
        5,
        5,
        5,
        5,
        5,
        5,
        5,
        5,
        5,
        5,
        5,
        5,
        5,
        5,
        5,
        5,
        5,
        5,
        5,
        5,
        5,
        5,
        5,
        5,
        5,
        5,
        5,
        5,
        5,
        5,
        5,
        5,
        5,
        5,
        5,
        5,
        5,
        5,
        5,
        5,
        5,
        5,
        5,
        5,
        5,
        5,
        5,
        5,
        5,
        5,
        5,
        5,
        5,
        5,
        5,
        5,
        5,
        5,
        5,
        5,
        5,
        5,
        5,
        5,
        5,
        5,
        5,
        5,
        5,
        5,
        5,
        5,
        5,
        5,
        5,
        5,
        5,
        5,
        5,
        5,
        5,
        5,
        5,
        5,
        5,
        5,
        5,
        5,
        5,
        5,
        5,
        5,
        5,
        5,
        5,
        5,
        5,
        5,
        5,
        5,
        5,
        5,
        5,
        5,
        5,
        5,
        5,
        5,
        5,
        5,
        5,
        5,
        5,
        5,
        5,
        5,
        5,
        5,
        5,
        5,
        5,
        5,
        5,
        5,
        5,
        5,
        5,
        5,
        5,
        5,
        5,
        5,
        5,
        5,
        5,
        5,
        5,
        5,
        5,
        5,
        5,
        5,
        5,
        5,
        5,
        5,
        5,
        5,
        5,
        5,
        5,
        5,
        5,
        5,
        5,
        5,
        5,
        5,
        5,
        5,
        5,
        5,
        5,
        5,
        5,
        5,
        5,
        5,
        5,
        5,
        5,
        5,
        5,
        5,
        5,
        5,
        5,
        5,
        5,
        5,
        5,
        5,
        5,
        5,
        5,
        5,
        5,
        5,
        5,
        5,
        5,
        5,
        5,
        5,
        5,
        5,
        5,
        5,
        5,
        5,
        5,
        5,
        5,
        5,
        5,
        5,
        5,
        5,
        5,
        5,
        5,
        5,
        5,
        5,
        5,
        5,
        5,
        5,
        5,
        5,
        5,
        5,
        5,
        5,
        5,
        5,
        5,
        5,
        5,
        5,
        5,
        5,
        5,
        5,
        5,
        5,
        5,
        5,
        5,
        5,
        5,
        5,
        5,
        5,
        5,
        5,
        5,
        5,
        5,
        5,
        5,
        5,
        5,
        5,
        5,
        5,
        5,
        5,
        5,
        5,
        5,
        5,
        5,
        5,
        5,
        5,
        5,
        5,
        5,
        5,
        5,
        5,
        5,
        5,
        5,
        5,
        5,
        5,
        5,
        5,
        5,
        5,
        5,
        5,
        5,
        5,
        5,
        5,
        5,
        5,
        5,
        5,
        5,
        5,
        5,
        5,
        5,
        5,
        5,
        5,
        5,
        5,
        5,
        5,
        5,
        5,
        5,
        5,
        5,
        5,
        5,
        5,
        5,
        5,
        5,
        5,
        5,
        5,
        5,
        5,
        5,
        5,
        5,
        5,
        5,
        5,
        5,
        5,
        5,
        5,
        5,
        5,
        5,
        5,
        5,
        5,
        5,
        5,
        5,
        5,
        5,
        5,
        5,
        5,
        5,
        5,
        5,
        5,
        5,
        5,
        5,
        5,
        5,
        5,
        5,
        5,
        5,
        5,
        5
      ],
      "opt_nodes_feats": {},
      "opt_edges_feats": {}
    }
  },
  "Config": {
    "reward_type": "num_msgs",
    "verbosity": "NONE",
    "verbosity_interval": 500
  },
  "Hyperparameters": {
    "n_episodes": 30000,
    "gamma": 0.97,
    "alpha": 0.0001,
    "K": 10,
    "Baseline": false
  },
  "Policy": {
    "type": "PtrNet",
    "optimizer": "Adam",
    "typecell": "LSTM",
    "n_outputs": 16,
    "n_embed": 128,
    "n_hidden": 128,
    "init_min": -0.08,
    "init_max": 0.08,
    "node_selector": "sampling"
  },
  "GNN": {
    "type": "Node2Vec",
    "dimensions": 128,
    "n_walks": 100,
    "walk_length": 5
  },
  "Output": {
    "graph_file": "./NPB_MG_64_16__RR.png",
    "output_file": "./NPB_MG_64_16_C_RR.json"
  },
  "Benchmark": {
		"name":             "NPB_MG_64_16_C",
	  "description":      "NAS Parallel Benchmark MG Class=C P=64 M=16 RR",
    "exec": "./Env/tLop/NPB_MG_64_16_C",
    "opts": "./Env/tLop/NPB_MG_64_16_C.json",
    "collective": "",
    "algorithm": "Graph-Based",
    "platform": "CIEMAT",
    "n_iter": 1,
    "optimal_mapping": [
      0,
      1,
      2,
      3,
      4,
      5,
      6,
      7,
      8,
      9,
      10,
      11,
      12,
      13,
      14,
      15,
      0,
      1,
      2,
      3,
      4,
      5,
      6,
      7,
      8,
      9,
      10,
      11,
      12,
      13,
      14,
      15,
      0,
      1,
      2,
      3,
      4,
      5,
      6,
      7,
      8,
      9,
      10,
      11,
      12,
      13,
      14,
      15,
      0,
      1,
      2,
      3,
      4,
      5,
      6,
      7,
      8,
      9,
      10,
      11,
      12,
      13,
      14,
      15
    ],
    "optimal_type": "RR"
  }
}
